{
    "zip": "72762-6999",
    "sector": "Consumer Defensive",
    "fullTimeEmployees": 137000,
    "longBusinessSummary": "Tyson Foods, Inc., together with its subsidiaries, operates as a food company worldwide. It operates through four segments: Beef, Pork, Chicken, and Prepared Foods. The company processes live fed cattle and live market hogs; fabricates dressed beef and pork carcasses into primal and sub-primal meat cuts, as well as case ready beef and pork, and fully cooked meats; raises and processes chickens into fresh, frozen, and value-added chicken products; and supplies poultry breeding stock; sells specialty products, such as hides and meats. It also manufactures and markets frozen and refrigerated food products, including ready-to-eat sandwiches, flame-grilled hamburgers, Philly steaks, pepperoni, bacon, breakfast sausage, turkey, lunchmeat, hot dogs, flour and corn tortilla products, appetizers, snacks, prepared meals, ethnic foods, side dishes, meat dishes, breadsticks, and processed meats under the Jimmy Dean, Hillshire Farm, Ball Park, Wright, State Fair, Aidells, and Gallo Salame brands. The company also offers its products under Tyson and ibp brands. It sells its products through its sales staff to grocery retailers, grocery wholesalers, meat distributors, warehouse club stores, military commissaries, industrial food processing companies, chain restaurants or their distributors, live markets, international export companies, and domestic distributors who serve restaurants and food service operations, such as plant and school cafeterias, convenience stores, hospitals, and other vendors, as well as through independent brokers and trading companies. The company was founded in 1935 and is headquartered in Springdale, Arkansas.",
    "city": "Springdale",
    "phone": "479 290 4000",
    "state": "AR",
    "country": "United States",
    "companyOfficers": [],
    "website": "https://www.tysonfoods.com",
    "maxAge": 1,
    "address1": "2200 West Don Tyson Parkway",
    "industry": "Farm Products",
    "ebitdaMargins": 0.12646,
    "profitMargins": 0.06476,
    "grossMargins": 0.14583,
    "operatingCashflow": 3840000000,
    "revenueGrowth": 0.118,
    "operatingMargins": 0.10106,
    "ebitda": 5950000128,
    "targetLowPrice": 78,
    "recommendationKey": "buy",
    "grossProfits": 6861000000,
    "freeCashflow": 3241374976,
    "targetMedianPrice": 89.5,
    "currentPrice": 85.64,
    "earningsGrowth": 1.074,
    "currentRatio": 1.553,
    "returnOnAssets": 0.08399,
    "numberOfAnalystOpinions": 12,
    "targetMeanPrice": 91.17,
    "debtToEquity": 55.287,
    "returnOnEquity": 0.18412,
    "targetHighPrice": 103,
    "totalCash": 2507000064,
    "totalDebt": 9870999552,
    "totalRevenue": 47048998912,
    "totalCashPerShare": 6.873,
    "financialCurrency": "USD",
    "revenuePerShare": 129.612,
    "quickRatio": 0.776,
    "recommendationMean": 2.2,
    "exchange": "NYQ",
    "shortName": "Tyson Foods, Inc.",
    "longName": "Tyson Foods, Inc.",
    "exchangeTimezoneName": "America/New_York",
    "exchangeTimezoneShortName": "EST",
    "isEsgPopulated": false,
    "gmtOffSetMilliseconds": "-18000000",
    "quoteType": "EQUITY",
    "symbol": "TSN",
    "messageBoardId": "finmb_190636",
    "market": "us_market",
    "annualHoldingsTurnover": null,
    "enterpriseToRevenue": 0.82,
    "beta3Year": null,
    "enterpriseToEbitda": 6.484,
    "52WeekChange": 0.32370305,
    "morningStarRiskRating": null,
    "forwardEps": 7.62,
    "revenueQuarterlyGrowth": null,
    "sharesOutstanding": 293071008,
    "fundInceptionDate": null,
    "annualReportExpenseRatio": null,
    "totalAssets": null,
    "bookValue": 48.556,
    "sharesShort": 3783734,
    "sharesPercentSharesOut": 0.0104,
    "fundFamily": null,
    "lastFiscalYearEnd": 1633132800,
    "heldPercentInstitutions": 0.85392,
    "netIncomeToCommon": 3047000064,
    "trailingEps": 8.34,
    "lastDividendValue": 0.46,
    "SandP52WeekChange": 0.26514983,
    "priceToBook": 1.7637367,
    "heldPercentInsiders": 0.02177,
    "nextFiscalYearEnd": 1696204800,
    "yield": null,
    "mostRecentQuarter": 1633132800,
    "shortRatio": 2.06,
    "sharesShortPreviousMonthDate": 1635465600,
    "floatShares": 287611727,
    "beta": 0.817142,
    "enterpriseValue": 38581653504,
    "priceHint": 2,
    "threeYearAverageReturn": null,
    "lastSplitDate": 856224000,
    "lastSplitFactor": "3:2",
    "legalType": null,
    "lastDividendDate": 1638230400,
    "morningStarOverallRating": null,
    "earningsQuarterlyGrowth": 1.072,
    "priceToSalesTrailing12Months": 0.66089094,
    "dateShortInterest": 1638230400,
    "pegRatio": 1.56,
    "ytdReturn": null,
    "forwardPE": 11.238845,
    "lastCapGain": null,
    "shortPercentOfFloat": 0.0147,
    "sharesShortPriorMonth": 4700118,
    "impliedSharesOutstanding": 363080992,
    "category": null,
    "fiveYearAverageReturn": null,
    "previousClose": 85.22,
    "regularMarketOpen": 85.09,
    "twoHundredDayAverage": 78.0393,
    "trailingAnnualDividendYield": 0.020887116,
    "payoutRatio": 0.2134,
    "volume24Hr": null,
    "regularMarketDayHigh": 85.735,
    "navPrice": null,
    "averageDailyVolume10Day": 2077490,
    "regularMarketPreviousClose": 85.22,
    "fiftyDayAverage": 82.4566,
    "trailingAnnualDividendRate": 1.78,
    "open": 85.09,
    "toCurrency": null,
    "averageVolume10days": 2077490,
    "expireDate": null,
    "algorithm": null,
    "dividendRate": 1.84,
    "exDividendDate": 1638230400,
    "circulatingSupply": null,
    "startDate": null,
    "regularMarketDayLow": 84.92,
    "currency": "USD",
    "trailingPE": 10.268585,
    "regularMarketVolume": 185530,
    "lastMarket": null,
    "maxSupply": null,
    "openInterest": null,
    "marketCap": 31094255616,
    "volumeAllCurrencies": null,
    "strikePrice": null,
    "averageVolume": 1851716,
    "dayLow": 84.92,
    "ask": 85.68,
    "askSize": 800,
    "volume": 185530,
    "fiftyTwoWeekHigh": 86.96,
    "fromCurrency": null,
    "fiveYearAvgDividendYield": 1.92,
    "fiftyTwoWeekLow": 62.51,
    "bid": 85.63,
    "tradeable": false,
    "dividendYield": 0.0216,
    "bidSize": 800,
    "dayHigh": 85.735,
    "regularMarketPrice": 85.64,
    "preMarketPrice": 85.405,
    "logo_url": "https://logo.clearbit.com/tysonfoods.com"
}