{
    "zip": "94568-7579",
    "sector": "Consumer Cyclical",
    "fullTimeEmployees": 93700,
    "longBusinessSummary": "Ross Stores, Inc., together with its subsidiaries, operates off-price retail apparel and home fashion stores under the Ross Dress for Less and dd's DISCOUNTS brands. Its stores primarily offer apparel, accessories, footwear, and home fashions. The company's Ross Dress for Less stores sell its products at department and specialty stores primarily to middle income households; and dd's DISCOUNTS stores sell its products at department and discount stores regular prices to customers from households with moderate income. As of September 27, 2021, it operated approximately 1,900 off-price apparel and home fashion stores in 40 states, the District of Columbia, and Guam. The company was incorporated in 1957 and is headquartered in Dublin, California.",
    "city": "Dublin",
    "phone": "925 965 4400",
    "state": "CA",
    "country": "United States",
    "companyOfficers": [],
    "website": "http://www.rossstores.com",
    "maxAge": 1,
    "address1": "5130 Hacienda Drive",
    "fax": "302 655 5049",
    "industry": "Apparel Retail",
    "ebitdaMargins": 0.14343001,
    "profitMargins": 0.07734,
    "grossMargins": 0.32836,
    "operatingCashflow": 3418906880,
    "revenueGrowth": 0.79,
    "operatingMargins": 0.12272,
    "ebitda": 2484894976,
    "targetLowPrice": 130,
    "recommendationKey": "buy",
    "grossProfits": 3534366000,
    "freeCashflow": 2678887168,
    "targetMedianPrice": 140,
    "currentPrice": 109.735,
    "earningsGrowth": 22.167,
    "currentRatio": 1.769,
    "returnOnAssets": 0.10646,
    "numberOfAnalystOpinions": 22,
    "targetMeanPrice": 140.47,
    "debtToEquity": 144.126,
    "returnOnEquity": 0.39576998,
    "targetHighPrice": 153,
    "totalCash": 5569071104,
    "totalDebt": 5626663936,
    "totalRevenue": 17325234176,
    "totalCashPerShare": 15.671,
    "financialCurrency": "USD",
    "revenuePerShare": 49.117,
    "quickRatio": 1.321,
    "recommendationMean": 2,
    "exchange": "NMS",
    "shortName": "Ross Stores, Inc.",
    "longName": "Ross Stores, Inc.",
    "exchangeTimezoneName": "America/New_York",
    "exchangeTimezoneShortName": "EST",
    "isEsgPopulated": true,
    "gmtOffSetMilliseconds": "-18000000",
    "underlyingSymbol": null,
    "quoteType": "EQUITY",
    "symbol": "ROST",
    "underlyingExchangeSymbol": null,
    "headSymbol": null,
    "messageBoardId": "finmb_33926",
    "uuid": "312ee907-969d-3ea1-8fa6-d5596a9418ed",
    "market": "us_market",
    "annualHoldingsTurnover": null,
    "enterpriseToRevenue": 2.216,
    "beta3Year": null,
    "enterpriseToEbitda": 15.45,
    "52WeekChange": null,
    "morningStarRiskRating": null,
    "forwardEps": 5.28,
    "revenueQuarterlyGrowth": null,
    "sharesOutstanding": 357120992,
    "fundInceptionDate": null,
    "annualReportExpenseRatio": null,
    "totalAssets": null,
    "bookValue": 10.229,
    "sharesShort": 3447804,
    "sharesPercentSharesOut": 0.0097,
    "fundFamily": null,
    "lastFiscalYearEnd": 1611964800,
    "heldPercentInstitutions": 0.88701,
    "netIncomeToCommon": 1339913984,
    "trailingEps": 2.441,
    "lastDividendValue": null,
    "SandP52WeekChange": null,
    "priceToBook": 10.727833,
    "heldPercentInsiders": 0.01935,
    "nextFiscalYearEnd": 1675036800,
    "yield": null,
    "mostRecentQuarter": 1627689600,
    "shortRatio": 1.81,
    "sharesShortPreviousMonthDate": 1628812800,
    "floatShares": 348471861,
    "beta": 1.041798,
    "enterpriseValue": 38390919168,
    "priceHint": 2,
    "threeYearAverageReturn": null,
    "lastSplitDate": 1434067200,
    "lastSplitFactor": "2:1",
    "legalType": null,
    "morningStarOverallRating": null,
    "earningsQuarterlyGrowth": 21.418,
    "priceToSalesTrailing12Months": 2.261942,
    "dateShortInterest": 1631664000,
    "pegRatio": 0.29,
    "ytdReturn": null,
    "forwardPE": 20.783144,
    "lastCapGain": null,
    "shortPercentOfFloat": 0.0115,
    "sharesShortPriorMonth": 4086984,
    "category": null,
    "fiveYearAverageReturn": null,
    "previousClose": 109.03,
    "regularMarketOpen": 109.5,
    "twoHundredDayAverage": 119.0745,
    "trailingAnnualDividendYield": 0.0052279187,
    "payoutRatio": 0.1508,
    "volume24Hr": null,
    "regularMarketDayHigh": 109.86,
    "navPrice": null,
    "averageDailyVolume10Day": 1793100,
    "regularMarketPreviousClose": 109.03,
    "fiftyDayAverage": 112.4176,
    "trailingAnnualDividendRate": 0.57,
    "open": 109.5,
    "averageVolume10days": 1793100,
    "expireDate": null,
    "algorithm": null,
    "dividendRate": 1.14,
    "exDividendDate": 1630627200,
    "circulatingSupply": null,
    "startDate": null,
    "regularMarketDayLow": 108.86,
    "currency": "USD",
    "trailingPE": 44.954937,
    "regularMarketVolume": 581076,
    "lastMarket": null,
    "maxSupply": null,
    "openInterest": null,
    "marketCap": 39188672512,
    "volumeAllCurrencies": null,
    "strikePrice": null,
    "averageVolume": 1965174,
    "dayLow": 108.86,
    "ask": 109.82,
    "askSize": 800,
    "volume": 581076,
    "fiftyTwoWeekHigh": 134.22,
    "fromCurrency": null,
    "fiveYearAvgDividendYield": 0.82,
    "fiftyTwoWeekLow": 103.62,
    "bid": 109.74,
    "tradeable": false,
    "dividendYield": 0.0106,
    "bidSize": 800,
    "dayHigh": 109.86,
    "regularMarketPrice": 109.735,
    "preMarketPrice": null,
    "logo_url": "https://logo.clearbit.com/rossstores.com"
}