{
    "zip": "73142",
    "sector": "Technology",
    "fullTimeEmployees": 4218,
    "longBusinessSummary": "Paycom Software, Inc. provides cloud-based human capital management (HCM) solution delivered as software-as-a-service for small to mid-sized companies in the United States. It offers functionality and data analytics that businesses need to manage the employment life cycle from recruitment to retirement. The company's HCM solution provides a suite of applications in the areas of talent acquisition, including applicant tracking, candidate tracker, background checks, on-boarding, e-verify, and tax credit services; and time and labor management, such as time and attendance, scheduling/schedule exchange, time-off requests, labor allocation, labor management reports/push reporting, and geofencing/geotracking. Its HCM solution also offers payroll applications comprising payroll and tax management, Paycom pay, expense management, mileage tracker/fixed and variable rates, garnishment management, and GL concierge applications; and talent management applications that include employee self-service, compensation budgeting, performance management, and Paycom learning, course content, and subscriptions, as well as my analytics, which offer employment predictor reporting. In addition, the company's HCM solution provides HR management applications comprising manager on-the-go that gives supervisors and managers the ability to perform a variety of tasks, such as approving time-off requests and expense reimbursements; direct data exchange; ask here, a tool for direct line of communication to ask work-related questions; document and checklist; government and compliance; benefits administration/benefits to carrier; COBRA administration; personnel action forms; surveys; and affordable care act applications. Paycom Software, Inc. was founded in 1998 and is headquartered in Oklahoma City, Oklahoma.",
    "city": "Oklahoma City",
    "phone": "405-722-6900",
    "state": "OK",
    "country": "United States",
    "companyOfficers": [],
    "website": "https://www.paycom.com",
    "maxAge": 1,
    "address1": "7501 West Memorial Road",
    "industry": "Software\u2014Application",
    "ebitdaMargins": 0.25885,
    "profitMargins": 0.17311001,
    "grossMargins": 0.88024,
    "operatingCashflow": 282516000,
    "revenueGrowth": 0.304,
    "operatingMargins": 0.22309,
    "ebitda": 256642000,
    "targetLowPrice": 415,
    "recommendationKey": "buy",
    "grossProfits": 743656000,
    "freeCashflow": 202889504,
    "targetMedianPrice": 567.5,
    "currentPrice": 356.83,
    "earningsGrowth": 0.106,
    "currentRatio": 1.074,
    "returnOnAssets": 0.04125,
    "numberOfAnalystOpinions": 16,
    "targetMeanPrice": 559.5,
    "debtToEquity": 12.27,
    "returnOnEquity": 0.23549,
    "targetHighPrice": 655,
    "totalCash": 230926000,
    "totalDebt": 101269000,
    "totalRevenue": 991484992,
    "totalCashPerShare": 3.982,
    "financialCurrency": "USD",
    "revenuePerShare": 17.155,
    "quickRatio": 0.082,
    "recommendationMean": 2,
    "exchange": "NYQ",
    "shortName": "Paycom Software, Inc.",
    "longName": "Paycom Software, Inc.",
    "exchangeTimezoneName": "America/New_York",
    "exchangeTimezoneShortName": "EST",
    "isEsgPopulated": false,
    "gmtOffSetMilliseconds": "-18000000",
    "underlyingSymbol": null,
    "quoteType": "EQUITY",
    "symbol": "PAYC",
    "underlyingExchangeSymbol": null,
    "headSymbol": null,
    "messageBoardId": "finmb_254225545",
    "uuid": "7074ae7c-b915-3b16-8f24-8e1864e2d20c",
    "market": "us_market",
    "annualHoldingsTurnover": null,
    "enterpriseToRevenue": 22.792,
    "beta3Year": null,
    "enterpriseToEbitda": 88.051,
    "52WeekChange": null,
    "morningStarRiskRating": null,
    "forwardEps": 5.63,
    "revenueQuarterlyGrowth": null,
    "sharesOutstanding": 60025800,
    "fundInceptionDate": null,
    "annualReportExpenseRatio": null,
    "totalAssets": null,
    "bookValue": 14.231,
    "sharesShort": 951249,
    "sharesPercentSharesOut": 0.015800001,
    "fundFamily": null,
    "lastFiscalYearEnd": 1609372800,
    "heldPercentInstitutions": 0.74508005,
    "netIncomeToCommon": 171640000,
    "trailingEps": 2.95,
    "lastDividendValue": null,
    "SandP52WeekChange": null,
    "priceToBook": 25.074133,
    "heldPercentInsiders": 0.15630999,
    "nextFiscalYearEnd": 1672444800,
    "yield": null,
    "mostRecentQuarter": 1632960000,
    "shortRatio": 2.93,
    "sharesShortPreviousMonthDate": 1636934400,
    "floatShares": 48597104,
    "beta": 1.474285,
    "enterpriseValue": 22597476352,
    "priceHint": 2,
    "threeYearAverageReturn": null,
    "lastSplitDate": null,
    "lastSplitFactor": null,
    "legalType": null,
    "morningStarOverallRating": null,
    "earningsQuarterlyGrowth": 0.105,
    "priceToSalesTrailing12Months": 21.602955,
    "dateShortInterest": 1639526400,
    "pegRatio": 3.34,
    "ytdReturn": null,
    "forwardPE": 63.380104,
    "lastCapGain": null,
    "shortPercentOfFloat": 0.0189,
    "sharesShortPriorMonth": 1066154,
    "category": null,
    "fiveYearAverageReturn": null,
    "previousClose": 356.83,
    "regularMarketOpen": 357.42,
    "twoHundredDayAverage": 422.533,
    "trailingAnnualDividendYield": null,
    "payoutRatio": 0,
    "volume24Hr": null,
    "regularMarketDayHigh": 362.82,
    "navPrice": null,
    "averageDailyVolume10Day": 481530,
    "regularMarketPreviousClose": 356.83,
    "fiftyDayAverage": 454.1306,
    "trailingAnnualDividendRate": null,
    "open": 357.42,
    "averageVolume10days": 481530,
    "expireDate": null,
    "algorithm": null,
    "dividendRate": null,
    "exDividendDate": null,
    "circulatingSupply": null,
    "startDate": null,
    "regularMarketDayLow": 350.03,
    "currency": "USD",
    "trailingPE": 120.95931,
    "regularMarketVolume": 1209763,
    "lastMarket": null,
    "maxSupply": null,
    "openInterest": null,
    "marketCap": 21419005952,
    "volumeAllCurrencies": null,
    "strikePrice": null,
    "averageVolume": 349217,
    "dayLow": 350.03,
    "ask": 400,
    "askSize": 800,
    "volume": 1209763,
    "fiftyTwoWeekHigh": 558.97,
    "fromCurrency": null,
    "fiveYearAvgDividendYield": null,
    "fiftyTwoWeekLow": 302.44,
    "bid": 0,
    "tradeable": false,
    "dividendYield": null,
    "bidSize": 1100,
    "dayHigh": 362.82,
    "regularMarketPrice": 356.83,
    "preMarketPrice": null,
    "logo_url": "https://logo.clearbit.com/paycom.com"
}